LICENSE
MANIFEST.in
README.rst
bjoern.py
setup.py
bjoern/_bjoernmodule.c
bjoern/common.c
bjoern/common.h
bjoern/filewrapper.c
bjoern/filewrapper.h
bjoern/portable_sendfile.c
bjoern/portable_sendfile.h
bjoern/py2py3.h
bjoern/request.c
bjoern/request.h
bjoern/server.c
bjoern/server.h
bjoern/statsd_tags.c
bjoern/statsd_tags.h
bjoern/wsgi.c
bjoern/wsgi.h
bjoern.egg-info/PKG-INFO
bjoern.egg-info/SOURCES.txt
bjoern.egg-info/dependency_links.txt
bjoern.egg-info/top_level.txt
http-parser/http_parser.c
http-parser/http_parser.h