Metadata-Version: 2.1
Name: bjoern
Version: 3.2.1
Summary: A screamingly fast Python 2 + 3 WSGI server written in C.
Home-page: https://github.com/jonashaag/bjoern
Author: Jonas Haag
Author-email: jonas@lophus.org
License: 2-clause BSD
Platform: UNKNOWN
Classifier: Development Status :: 4 - Beta
Classifier: License :: OSI Approved :: BSD License
Classifier: Programming Language :: C
Classifier: Programming Language :: Python :: 2
Classifier: Programming Language :: Python :: 3
Classifier: Topic :: Internet :: WWW/HTTP :: WSGI :: Server
License-File: LICENSE
